CHANGELOG.md
CONTRIBUTING.md
LICENSE
cachalot/__init__.py
cachalot-1.5.0.dist-info/LICENSE
cachalot-1.5.0.dist-info/WHEEL
cachalot-1.5.0.dist-info/METADATA
cachalot-1.5.0.dist-info/RECORD
