Metadata-Version: 2.1
Name: cachalot
Version: 1.5.0
Summary: Minimal persistent memoization cache
Home-page: https://radek-sprta.gitlab.io/Cachalot/
License: MIT
Keywords: memoization,cache
Author: Radek Sprta
Author-email: mail@radeksprta.eu
Requires-Python: >=3.5,<4.0
Classifier: Development Status :: 5 - Production/Stable
Classifier: License :: OSI Approved :: MIT License
Classifier: Natural Language :: English
Classifier: Operating System :: OS Independent
Classifier: Programming Language :: Python :: 3
Classifier: Programming Language :: Python :: 3.5
Classifier: Programming Language :: Python :: 3.6
Classifier: Programming Language :: Python :: 3.7
Classifier: Programming Language :: Python :: 3.8
Classifier: Topic :: Database
Classifier: Topic :: Software Development :: Libraries
Requires-Dist: importlib_metadata (>=1.6.0,<2.0.0); python_version < "3.8"
Requires-Dist: jsonpickle
Requires-Dist: tinydb (>=4,<5)
Requires-Dist: tinydb-smartcache
Project-URL: Documentation, https://radek-sprta.gitlab.io/Cachalot/
Project-URL: Repository, https://gitlab.com/radek-sprta/Cachalot
